sphinx_emf/__init__.py
sphinx_emf/base_templates/content.rst.j2
sphinx_emf/base_templates/content_direct.rst.j2
sphinx_emf/base_templates/content_direct_field.rst.j2
sphinx_emf/base_templates/content_nested.rst.j2
sphinx_emf/base_templates/content_nested_needs.rst.j2
sphinx_emf/base_templates/macros.j2
sphinx_emf/base_templates/need.rst.j2
sphinx_emf/base_templates/needs.rst.j2
sphinx_emf/base_templates/options.rst.j2
sphinx_emf/base_templates/options_field.rst.j2
sphinx_emf/base_templates/options_fields.rst.j2
sphinx_emf/base_templates/options_link.rst.j2
sphinx_emf/base_templates/options_links.rst.j2
sphinx_emf/builder.py
sphinx_emf/cli.py
sphinx_emf/config/__init__.py
sphinx_emf/config/invert.py
sphinx_emf/config/model.py
sphinx_emf/config/validate.py
sphinx_emf/ecore/__init__.py
sphinx_emf/ecore/ecore_io.py
sphinx_emf/main.py
sphinx_emf/setup.py
sphinx_emf/sphinx_logging.py
sphinx_emf/user_hooks/escape_rst.py
sphinx_emf/utils.py
sphinx_emf-0.2.0.dist-info/entry_points.txt
sphinx_emf-0.2.0.dist-info/LICENSE
sphinx_emf-0.2.0.dist-info/WHEEL
sphinx_emf-0.2.0.dist-info/METADATA
sphinx_emf-0.2.0.dist-info/RECORD
